canonicalwebteam/__init__.py
canonicalwebteam/flask_vite/__init__.py
canonicalwebteam/flask_vite/exceptions.py
canonicalwebteam/flask_vite/extension.py
canonicalwebteam/flask_vite/impl/__init__.py
canonicalwebteam/flask_vite/impl/base.py
canonicalwebteam/flask_vite/impl/dev.py
canonicalwebteam/flask_vite/impl/prod.py
canonicalwebteam/flask_vite/types.py
canonicalwebteam/flask_vite/utils.py
canonicalwebteam_flask_vite-0.4.0.dist-info/METADATA
canonicalwebteam_flask_vite-0.4.0.dist-info/WHEEL
canonicalwebteam_flask_vite-0.4.0.dist-info/licenses/LICENSE
canonicalwebteam_flask_vite-0.4.0.dist-info/RECORD
