Metadata-Version: 2.4
Name: canonicalwebteam.flask-vite
Version: 0.4.0
Summary: A Flask extension that integrates with Vite
License-Expression: LGPL-3.0
License-File: LICENSE
Author: Canonical Web Team
Author-email: webteam@canonical.com
Requires-Python: >=3.10,<4.0
Classifier: Programming Language :: Python :: 3
Classifier: Programming Language :: Python :: 3.10
Classifier: Programming Language :: Python :: 3.11
Classifier: Programming Language :: Python :: 3.12
Classifier: Programming Language :: Python :: 3.13
Classifier: Programming Language :: Python :: 3.14
Requires-Dist: flask (>=2.3,<3.0)
Project-URL: Homepage, https://github.com/canonical/canonicalwebteam.flask-vite
Project-URL: Issues, https://github.com/canonical/canonicalwebteam.flask-vite/issues
